spotifycodegen/__init__.py
spotifycodegen/cli.py
spotifycodegen/main.py
spotifycodegen-0.1.2.dist-info/entry_points.txt
spotifycodegen-0.1.2.dist-info/WHEEL
spotifycodegen-0.1.2.dist-info/METADATA
spotifycodegen-0.1.2.dist-info/RECORD
