Metadata-Version: 2.1
Name: spotifycodegen
Version: 0.1.2
Summary: 
Home-page: https://github.com/tilschuenemann/spotifycodegen
Keywords: spotify,cover,art,spotify-api,scan,uri,url,query,spotipy,code
Author: schuenemann
Requires-Python: >=3.10,<4.0
Classifier: Development Status :: 3 - Alpha
Classifier: Intended Audience :: Developers
Classifier: Intended Audience :: End Users/Desktop
Classifier: Operating System :: MacOS
Classifier: Operating System :: Microsoft :: Windows
Classifier: Operating System :: POSIX :: Linux
Classifier: Programming Language :: Python :: 3
Classifier: Programming Language :: Python :: 3.10
Classifier: Programming Language :: Python :: 3.11
Classifier: Programming Language :: Python :: 3.10
Classifier: Programming Language :: Python :: 3.11
Requires-Dist: colorthief (>=0.2.1,<0.3.0)
Requires-Dist: pillow (>=9.3.0,<10.0.0)
Requires-Dist: spotipy (>=2.21.0,<3.0.0)
Requires-Dist: tqdm (>=4.64.1,<5.0.0)
Project-URL: Repository, https://github.com/tilschuenemann/spotifycodegen
